clockclock24_py/__init__.py
clockclock24_py/main.py
clockclock24_py/components/__init__.py
clockclock24_py/components/clock.py
clockclock24_py/components/clockclock24.py
clockclock24_py/components/needle.py
clockclock24_py/components/number.py
clockclock24_py/constants/__init__.py
clockclock24_py/constants/config.py
clockclock24_py/constants/numbers.py
clockclock24_py/constants/shapes.py
clockclock24_py/constants/utils.py
clockclock24_py/tests/__init__.py
clockclock24_py/tests/test_engine.py
clockclock24_py/tests/test_timers.py
clockclock24_py/tests/test_utils.py
clockclock24_py/utils/__init__.py
clockclock24_py/utils/engine.py
clockclock24_py/utils/timers.py
clockclock24_py/utils/utils.py
clockclock24_py-1.0.1.dist-info/licenses/LICENSE.txt
clockclock24_py-1.0.1.dist-info/METADATA
clockclock24_py-1.0.1.dist-info/WHEEL
clockclock24_py-1.0.1.dist-info/entry_points.txt
clockclock24_py-1.0.1.dist-info/top_level.txt
clockclock24_py-1.0.1.dist-info/RECORD
