Metadata-Version: 2.4
Name: clockclock24-py
Version: 1.0.1
Summary: Python port of ClockClock24 - A kinetic clock display
Author: TBOY1337
Keywords: clock,animation,tkinter
Classifier: Programming Language :: Python :: 3
Classifier: License :: OSI Approved :: MIT License
Classifier: Operating System :: OS Independent
Requires-Python: >=3.6
License-File: LICENSE.txt
Dynamic: license-file
